ptrail/__init__.py
ptrail/GUI/GUI_driver.py
ptrail/GUI/InputDialog.py
ptrail/GUI/SearchableComboBox.py
ptrail/GUI/Table.py
ptrail/GUI/__init__.py
ptrail/GUI/gui.py
ptrail/GUI/handler.py
ptrail/core/Datasets.py
ptrail/core/TrajectoryDF.py
ptrail/core/__init__.py
ptrail/features/__init__.py
ptrail/features/contextual_features.py
ptrail/features/helper_functions.py
ptrail/features/kinematic_features.py
ptrail/features/temporal_features.py
ptrail/preprocessing/__init__.py
ptrail/preprocessing/filters.py
ptrail/preprocessing/helpers.py
ptrail/preprocessing/interpolation.py
ptrail/preprocessing/statistics.py
ptrail/utilities/DistanceCalculator.py
ptrail/utilities/__init__.py
ptrail/utilities/constants.py
ptrail/utilities/conversions.py
ptrail/utilities/exceptions.py
ptrail/visualization/HydrationTrends.py
ptrail/visualization/InteractiveDonut.py
ptrail/visualization/TrajPlotter.py
ptrail/visualization/__init__.py
ptrail/visualization/statViz.py
ptrail-1.0.dist-info/LICENSE
ptrail-1.0.dist-info/METADATA
ptrail-1.0.dist-info/WHEEL
ptrail-1.0.dist-info/top_level.txt
ptrail-1.0.dist-info/RECORD
