Metadata-Version: 2.1
Name: ptrail
Version: 1.0
Summary: PTRAIL: A Mobility-data Preprocessing Library using parallel computation.
Home-page: https://github.com/YakshHaranwala/PTRAIL.git
Maintainer: PTRAIL Developers
Maintainer-email: yjharanwala@mun.ca
License: new BSD
Platform: UNKNOWN
Classifier: Intended Audience :: Science/Research
Classifier: Intended Audience :: Developers
Classifier: License :: OSI Approved
Classifier: Programming Language :: Python
Classifier: Topic :: Software Development
Classifier: Topic :: Scientific/Engineering
Classifier: Operating System :: OS Independent
Classifier: Programming Language :: Python :: 3
Requires-Python: >=3.6
License-File: LICENSE
Requires-Dist: numpy>=1.20
Requires-Dist: hampel>=0.0.5
Requires-Dist: pandas>=1.2.5
Requires-Dist: scipy>=1.6.2
Requires-Dist: folium>=0.12
Requires-Dist: osmnx>=1.1.1
Requires-Dist: geopandas>=0.8.1
Requires-Dist: shapely
Requires-Dist: IPython>=7.27.0
Requires-Dist: ipywidgets>=7.6.5
Requires-Dist: plotly>=5.3.1
Requires-Dist: matplotlib>=3.3.4
Requires-Dist: seaborn>=0.11.2
Requires-Dist: PyQt5
Requires-Dist: scikit-learn>=0.24.2
